setup.py
yearonedb/__init__.py
yearonedb/factor_db.py
yearonedb.egg-info/PKG-INFO
yearonedb.egg-info/SOURCES.txt
yearonedb.egg-info/dependency_links.txt
yearonedb.egg-info/not-zip-safe
yearonedb.egg-info/requires.txt
yearonedb.egg-info/top_level.txt