Metadata-Version: 1.0
Name: yearonedb
Version: 1.0.0
Summary: Hoard the mining
Home-page: http://github.com/hyqLeonardo/yearonedb
Author: Leonardo
Author-email: hyq335335@163.com
License: MIT
Platform: UNKNOWN
